<?xml version="1.0" encoding="utf-8"?>
<!DOCTYPE hibernate-mapping PUBLIC "-//Hibernate/Hibernate Mapping DTD 3.0//EN"
"http://www.hibernate.org/dtd/hibernate-mapping-3.0.dtd">
<!-- Mapping file autogenerated by MyEclipse Persistence Tools -->
<hibernate-mapping>
	<class name="com.k9sv.domain.pojo.Address" table="address">
		<id name="id" type="int">
			<column name="id" />
			<generator class="native" />
		</id>
		<property name="uid" type="int">
			<column name="uid" />
		</property>
		<property name="name" type="java.lang.String">
			<column name="name" />
		</property>
		<property name="telephone" type="java.lang.String">
			<column name="telephone" />
		</property>
		<property name="address" type="java.lang.String">
			<column name="address" />
		</property>
		<property name="deleted" type="int">
			<column name="deleted" />
		</property>
		<property name="state" type="int">
			<column name="state">
				<comment>设置默认地址 1为默认地址</comment>
			</column>
		</property>
	</class>
</hibernate-mapping>
