<?xml version="1.0" encoding="utf-8"?>
<!DOCTYPE hibernate-mapping PUBLIC "-//Hibernate/Hibernate Mapping DTD 3.0//EN"
"http://www.hibernate.org/dtd/hibernate-mapping-3.0.dtd">
<!-- Mapping file autogenerated by MyEclipse Persistence Tools -->
<hibernate-mapping>
	<class name="com.k9sv.domain.pojo.Buy" table="buy">
		<id name="id" type="java.lang.String">
			<column name="id" />
			<generator class="assigned" />
		</id>
		<property name="uid" type="int">
			<column name="uid">
				<comment>用户id</comment>
			</column>
		</property>
		<property name="addressid" type="int">
			<column name="addressid">
				<comment>地址id</comment>
			</column>
		</property>
		<property name="state" type="int">
			<column name="state">
				<comment>购买状态 0待付款 1付款成功</comment>
			</column>
		</property>
		<property name="name" type="java.lang.String">
			<column name="name" />
		</property>
		<property name="telephone" type="java.lang.String">
			<column name="telephone">
				<comment>收货人电话</comment>
			</column>
		</property>
		<property name="address" type="java.lang.String">
			<column name="address">
				<comment>收货地址</comment>
			</column>
		</property>
		<property name="buytime" type="java.util.Date">
			<column name="buytime" length="19">
				<comment>购买时间</comment>
			</column>
		</property>
		<property name="paytype" type="int">
			<column name="paytype">
				<comment>付款方式 0为微信1为支付宝</comment>
			</column>
		</property>
		<property name="paycount" type="java.lang.Float">
			<column name="paycount">
				<comment>总金额</comment>
			</column>
		</property>
		<property name="noncestr" type="java.lang.String">
			<column name="noncestr">
				<comment>随机字符串 判断微信回调</comment>
			</column>
		</property>
		<property name="gold" type="int">
			<column name="gold">
				<comment>订单使用金币数</comment>
			</column>
		</property>
		<property name="deleted" type="int">
			<column name="deleted">
				<comment></comment>
			</column>
		</property>
		<property name="express" type="java.lang.String">
			<column name="express">
				<comment>快递</comment>
			</column>
		</property>
		<property name="oddNumbers" type="java.lang.String">
			<column name="oddnumbers">
				<comment>单号</comment>
			</column>
		</property>
		<set name="buyinfors" inverse="true" lazy="false" cascade="delete"
			order-by="id asc" table="buy_infor">
			<key column="buyid"></key>
			<one-to-many class="com.k9sv.domain.pojo.BuyInfo" />
			
		</set>
	</class>
</hibernate-mapping>
